hdf5_vds_check.py
hdf5_vds_check-1.1.dist-info/entry_points.txt
hdf5_vds_check-1.1.dist-info/licenses/LICENSE
hdf5_vds_check-1.1.dist-info/WHEEL
hdf5_vds_check-1.1.dist-info/METADATA
hdf5_vds_check-1.1.dist-info/RECORD
