Metadata-Version: 2.5
Name: hdf5_vds_check
Version: 1.1
Summary: Check access to the source files of virtual datasets
Author-email: European XFEL GmbH <da-support@xfel.eu>
Requires-Python: >=3.6
License-Expression: BSD-3-Clause
License-File: LICENSE
Requires-Dist: h5py >=2.9.0
Project-URL: Source, https://github.com/European-XFEL/hdf5-vds-check
Import-Name: hdf5_vds_check
